{"githubUsername":"mxr-Lee","blogTitle":"某些人","blogDescribe":"Bruce Lee.Faye Wong.JKD.ZBrush.Windows","htmlTitle":"JKD-Lee","fontColor":"#ffffff","useBackgroundImage":false,"backgroundColorLeft":"#171717","backgroundColorRight":"#3A3838","audioUrl":"http://183.203.30.13/amobile.music.tc.qq.com/C400002WEvtX2B1h0v.m4a?guid=6442796980&vkey=4A86F15700EFCC31571E25B83CC117956A29159350A1D8EFC10CD9A33BE707353D96EECFCFBE6A38EE19CFAED3125C24CDA127524C873707&uin=0&fromtag=66","mini":true,"webSites":[],"audioAutoPlay":true}